moonshot/__init__.py
moonshot/__main__.py
moonshot/api.py
moonshot/data/connectors/claude2.py
moonshot/data/connectors/hf-gpt2.py
moonshot/data/connectors/hf-llama2-13b-gptq.py
moonshot/data/connectors/openai-gpt35-turbo-16k.py
moonshot/data/connectors/openai-gpt35.py
moonshot/data/connectors/openai-gpt4.py
moonshot/data/connectors-endpoints/test-openai-endpoint.json
moonshot/data/context-strategy/add_previous_prompt.py
moonshot/data/cookbooks/bbq-lite-age-cookbook.json
moonshot/data/cookbooks/cbbq-amb-cookbook.json
moonshot/data/cookbooks/cbbq-disamb-cookbook.json
moonshot/data/cookbooks/chinese-cookbook.json
moonshot/data/cookbooks/common-risk-easy.json
moonshot/data/cookbooks/common-risk-hard.json
moonshot/data/cookbooks/evaluation-catalogue-cookbook.json
moonshot/data/cookbooks/leaderboard-cookbook.json
moonshot/data/cookbooks/legal-summarisation.json
moonshot/data/cookbooks/tamil-language-cookbook.json
moonshot/data/cookbooks/truthful-cookbook.json
moonshot/data/databases/placeholder
moonshot/data/datasets/advglue-all.json
moonshot/data/datasets/advglue-mnli-adv.json
moonshot/data/datasets/advglue-mnli-benign.json
moonshot/data/datasets/advglue-mnlimm-adv.json
moonshot/data/datasets/advglue-mnlimm-benign.json
moonshot/data/datasets/advglue-qnli-adv.json
moonshot/data/datasets/advglue-qnli-benign.json
moonshot/data/datasets/advglue-qqp-adv.json
moonshot/data/datasets/advglue-qqp-benign.json
moonshot/data/datasets/advglue-rte-adv.json
moonshot/data/datasets/advglue-rte-benign.json
moonshot/data/datasets/advglue-sst2-adv.json
moonshot/data/datasets/advglue-sst2-benign.json
moonshot/data/datasets/analogical-similarity.json
moonshot/data/datasets/arc-challenge.json
moonshot/data/datasets/arc-easy.json
moonshot/data/datasets/auto-categorisation.json
moonshot/data/datasets/bbq-ambiguous.json
moonshot/data/datasets/bbq-disamb.json
moonshot/data/datasets/bbq-full.json
moonshot/data/datasets/bbq-lite-age-ambiguous.json
moonshot/data/datasets/bbq-lite-age-disamb.json
projectmoonshot_imda-0.3.4.dist-info/METADATA
projectmoonshot_imda-0.3.4.dist-info/WHEEL
projectmoonshot_imda-0.3.4.dist-info/licenses/AUTHORS.md
projectmoonshot_imda-0.3.4.dist-info/licenses/LICENSE
projectmoonshot_imda-0.3.4.dist-info/licenses/NOTICES
projectmoonshot_imda-0.3.4.dist-info/RECORD
