Metadata-Version: 2.3
Name: projectmoonshot-imda
Version: 0.3.4
Summary: A simple and modular tool to evaluate and red-team any LLM application.
Project-URL: Repository, https://github.com/moonshot-admin/moonshot
Project-URL: Documentation, https://moonshot-admin.github.io/moonshot/
Project-URL: Issues, https://github.com/moonshot-admin/moonshot/issues
Author-email: The Moonshot Team <our.moonshot.team@gmail.com>
License: Apache-2.0
License-File: AUTHORS.md
License-File: LICENSE
License-File: NOTICES
Classifier: Development Status :: 3 - Alpha
Classifier: License :: OSI Approved :: Apache Software License
Classifier: Programming Language :: Python :: 3
Classifier: Programming Language :: Python :: 3.11
Requires-Python: >=3.11
Requires-Dist: aiohttp==3.9.3
Requires-Dist: aiometer==0.5.0
Requires-Dist: anthropic==0.20.0
Requires-Dist: bert-score==0.3.13
Requires-Dist: ijson==3.2.3
Requires-Dist: jinja2==3.1.3
Requires-Dist: nltk==3.8.1
Requires-Dist: openai==0.28.1
Requires-Dist: py-readability-metrics==1.4.5
Requires-Dist: pylcs==0.1.1
Requires-Dist: python-dotenv==1.0.1
Requires-Dist: python-slugify==8.0.4
Requires-Dist: rouge-score==0.1.2
Requires-Dist: rouge==1.0.1
Requires-Dist: sentence-transformers==2.5.1
Requires-Dist: spacy==3.7.4
Provides-Extra: all
Requires-Dist: projectmoonshot-imda[cli]; extra == 'all'
Requires-Dist: projectmoonshot-imda[web-api]; extra == 'all'
Provides-Extra: cli
Requires-Dist: cmd2==2.4.3; extra == 'cli'
Requires-Dist: rich==13.7.1; extra == 'cli'
Provides-Extra: web-api
Requires-Dist: dependency-injector==4.41.0; extra == 'web-api'
Requires-Dist: fastapi==0.110.0; extra == 'web-api'
Requires-Dist: typing-extensions==4.10.0; extra == 'web-api'
Requires-Dist: uvicorn==0.28.0; extra == 'web-api'
